[
  {"key": "Delayed trigger", "verdict": "doubtful", "ru": "Отложенный триггер", "note": "имя объекта в палитре редактора уровней; не уверен, попадает ли в игру"},
  {"key": "Destructible metal crate", "verdict": "doubtful", "ru": "Разрушаемый металлический ящик", "note": "имя объекта в палитре редактора уровней; не уверен, попадает ли в игру"},
  {"key": "Destructible metal crate. Always drops a weapon, as long as someone has been killed", "verdict": "skip", "ru": "", "note": "инспекторский тултип-описание поведения объекта (LevelPartGame)"},
  {"key": "Destructible pallet", "verdict": "doubtful", "ru": "Разрушаемый поддон", "note": "имя объекта в палитре редактора уровней; не уверен, попадает ли в игру"},
  {"key": "Destructible pallet piece", "verdict": "doubtful", "ru": "Кусок разрушаемого поддона", "note": "имя объекта в палитре редактора уровней; не уверен, попадает ли в игру"},
  {"key": "Destructible pallet that slides on the ground", "verdict": "skip", "ru": "", "note": "инспекторский тултип-описание поведения объекта (LevelPartGame)"},
  {"key": "Destructible steel barrel", "verdict": "doubtful", "ru": "Разрушаемая стальная бочка", "note": "имя объекта в палитре редактора уровней; не уверен, попадает ли в игру"},
  {"key": "Destructible vehicle", "verdict": "doubtful", "ru": "Разрушаемый транспорт", "note": "имя объекта в палитре редактора уровней; не уверен, попадает ли в игру"},
  {"key": "Destructible wooden crate", "verdict": "doubtful", "ru": "Разрушаемый деревянный ящик", "note": "имя объекта в палитре редактора уровней; не уверен, попадает ли в игру"},
  {"key": "Destructible wooden crate. Drops no weapons", "verdict": "skip", "ru": "", "note": "инспекторский тултип-описание поведения объекта (LevelPartGame)"},
  {"key": "Dexterous and frail", "verdict": "translate", "ru": "Ловкий и хрупкий", "note": ""},
  {"key": "Dexterous, but frail", "verdict": "translate", "ru": "Ловкий, но хрупкий", "note": ""},
  {"key": "Different species have different lung capacities.", "verdict": "translate", "ru": "У разных видов разный объём лёгких.", "note": ""},
  {"key": "Dimension Shifter", "verdict": "doubtful", "ru": "Сдвигатель измерений", "note": "название музыкального трека (MusicClip), не уверен что отображается игроку"},
  {"key": "dingu s", "verdict": "translate", "ru": "дингу с", "note": "видимый внутриигровой текст (надпись), сохранён намеренно сломанный регистр/пробел"},
  {"key": "Disables camera smoothing (Instantly snaps to your character and cursor)", "verdict": "translate", "ru": "Отключает сглаживание камеры (мгновенно прыгает к персонажу и курсору)", "note": ""},
  {"key": "Disables rain/snow particles, which might help with recording\\nRecommended to keep off", "verdict": "translate", "ru": "Отключает частицы дождя/снега, что может помочь при записи\\nРекомендуется держать выключенным", "note": ""},
  {"key": "Discord Server", "verdict": "translate", "ru": "Сервер Discord", "note": ""},
  {"key": "DiscordButton, Assembly-CSharp", "verdict": "skip", "ru": "", "note": "имя ассета/типа (Assembly-CSharp)"},
  {"key": "Displays the relevant key when near a weapon/button", "verdict": "translate", "ru": "Показывает нужную клавишу рядом с оружием/кнопкой", "note": ""},
  {"key": "Distortion zone", "verdict": "doubtful", "ru": "Зона искажения", "note": "имя объекта в палитре редактора уровней; не уверен, попадает ли в игру"},
  {"key": "Distorts the screen when the player is close to it. Distance dictates how far away from the object the camera starts getting distorted", "verdict": "skip", "ru": "", "note": "инспекторский тултип-описание поведения объекта (LevelPartGame)"},
  {"key": "do you really have nothing better to do", "verdict": "translate", "ru": "тебе правда больше нечем заняться", "note": ""},
  {"key": "Does a variety of things when triggered. Set the action to 3 to end the level. See the guide channel for details!!!", "verdict": "skip", "ru": "", "note": "инспекторский тултип для разработчика в редакторе уровней (LevelPartGame)"},
  {"key": "Don't get caught up\\non these.", "verdict": "translate", "ru": "Не запутайся\\nв них.", "note": ""},
  {"key": "Don't get too attached to your victims.", "verdict": "translate", "ru": "Не привязывайся к своим жертвам.", "note": ""},
  {"key": "Door A", "verdict": "translate", "ru": "Дверь A", "note": ""},
  {"key": "Door ID", "verdict": "skip", "ru": "", "note": "имя поля-параметра в редакторе уровней (LevelPartGame)"}
]
