{"BARON": {"names": ["Aegis", "Alexander", "Alfred", "Alphred", "Armstrong", "Arnold", "Articulated In Wisdom", "Atticus", "Augustus", "Azazel", "Barrett", "Beast", "Benjamin", "Bertrand", "Bishop", "Boar", "Boulder", "Brawn", "Brutus", "Buck", "Buddy", "Bull", "Burke", "Captain", "Ceasar", "Chef", "Church", "Claymore", "Commando", "Conwell", "Cordius", "Corvus", "Crusher", "Cyrus", "David", "Deacon", "Desmond", "Diesal", "Duke", "Easel", "Ezekiel", "Fortus", "Freckles", "Frederick", "Gabriel", "Ganymede", "Gaston", "Germaine", "Gerson", "Giant", "Godric", "Golem", "Gregori", "Griffan", "Gustav", "Hammer", "Hammerhead", "Harold", "Henry", "Hercules", "Hulk", "Iferit", "Jebediah", "Joel", "Joseph", "Julius", "King", "Knight", "Krinkels", "Last Poem", "Leviathan", "Lord", "Lordran", "Luthor", "Magnus", "Manuel", "Marcus", "Mendel", "Michael", "Napoleon", "Njord", "Odell", "Orion", "Orthus", "Overlord", "Overseer", "Phil", "Priest", "Professor", "Raymon", "Rhino", "Ronteal", "Rosenburg", "Russell", "Saint", "Saladin", "Salvadore", "Sanchez", "Sanctus", "Sanford", "Senior", "Sergey", "Seven Red Suns", "Shephard", "Sigmund", "Simeon", "Sinclair", "Smith", "Socrates", "Solomon", "Sword", "Thomas", "Titus", "Tower", "Tyrant", "Ulof", "Ulyesses", "Vernon", "Vinny", "Warhead", "Warrior", "Weston", "Winston", "Wise One", "Wolzal", "Xerxes", "Xulthur", "Yseult", "Zeus", "Zweihander"], "canon": {"Alexander": "Александр", "Armstrong": "Армстронг", "Arnold": "Арнольд", "Atticus": "Аттикус", "Bishop": "Бишоп", "Boar": "Кабан", "Brutus": "Брут", "Buck": "Бак", "Buddy": "Бадди", "Captain": "Капитан", "Chef": "Шеф", "Church": "Церковь", "Commando": "Коммандо", "Conwell": "Конвелл", "Corvus": "Корвус", "Cyrus": "Кир", "David": "Дэвид", "Deacon": "Дикон", "Desmond": "Десмонд", "Easel": "Изель", "Gabriel": "Гэбриэл", "Gerson": "Герсон", "Gregori": "Григорий", "Henry": "Генри", "Hulk": "Халк", "Jebediah": "Джебедайя", "Joseph": "Джозеф", "Krinkels": "Кринкелс", "Luthor": "Лютор", "Manuel": "Мануэль", "Mendel": "Мендель", "Odell": "Оделл", "Orion": "Орион", "Overseer": "Надзиратель", "Phil": "Фил", "Priest": "Священник", "Raymon": "Реймон", "Ronteal": "Ронтил", "Rosenburg": "Розенберг", "Saint": "Святой", "Sanford": "Сэнфорд", "Sergey": "Сергей", "Simeon": "Симеон", "Sinclair": "Синклер", "Smith": "Смит", "Socrates": "Сократ", "Sword": "Меч", "Thomas": "Томас", "Ulof": "Улоф", "Vernon": "Вернон", "Weston": "Уэстон", "Yseult": "Изольда"}}, "CHIK": {"names": ["Adachi", "Aija", "Ambrose", "Anim", "Anoth", "Arct", "Artificer", "Ashley", "Bailey", "Beverly", "Briar", "Brook", "Bugeye", "Buzz", "Candle", "Candy", "Casi", "Cassidy", "Celeste", "Chef", "Chiki", "Choi", "Cocoa", "Corvi", "Corwin", "Cricket", "Dancer", "Dew", "Dext", "Dust", "Ellie", "Elliot", "Elwood", "Ember", "Engie", "Ewan", "Fable", "Feri", "Fern", "Flappy", "Foxtrot", "Fuzzy", "Gabe", "Galvan", "Garand", "Glimmer", "Glock", "Grace", "Gump", "Gunsmith", "Hunter", "Ignius", "Irwin", "Isaac", "Isaiah", "Ixin", "Journey", "Kaleb", "Kasey", "Keon", "Kirby", "Koy", "Kurfus", "Lachlan", "Lampy", "Lanian", "Laz", "Lennon", "Leon", "Lint", "Llamar", "Lordran", "Lynn", "M", "Majori", "Majul", "Medic", "Melvin", "Messiah", "Micah", "Misha", "Moth", "Muldraugh", "Mx", "Nabi", "Nico", "Nightwatcher", "Officer", "Omega", "Operator", "Oscar", "Owl", "Pate", "Peyton", "Pheonix", "Philip", "Pincer", "Pink", "Pinky", "Pittie", "Pretty", "Proto", "Punk", "Quincy", "Radi", "Reaver", "Reese", "Robin", "Roux", "Savvy", "Shelby", "Shia", "Snappy", "Solar", "Stark", "Stitch", "Tacti", "Tali", "Thomi", "Tinkerer", "Trill", "Trim", "Umbra", "Unit", "Vex", "Vibi", "Virgo", "Wanderer", "Watcher", "Weston", "Wick", "Wing", "Yuliea", "Zeal", "Zey", "Zhang"], "canon": {"Adachi": "Адати", "Aija": "Айя", "Anim": "Аним", "Anoth": "Анот", "Arct": "Аркт", "Artificer": "Техник", "Ashley": "Эшли", "Beverly": "Беверли", "Brook": "Брук", "Buzz": "Базз", "Casi": "Каси", "Celeste": "Селеста", "Chef": "Шеф", "Choi": "Чой", "Cocoa": "Какао", "Dancer": "Танцор", "Dew": "Роса", "Dext": "Декст", "Elliot": "Эллиот", "Elwood": "Элвуд", "Ember": "Эмбер", "Engie": "Инжи", "Fable": "Фейбл", "Feri": "Фери", "Fern": "Папоротник", "Fuzzy": "Пушистик", "Gabe": "Гейб", "Garand": "Гаранд", "Glock": "Глок", "Gump": "Гамп", "Gunsmith": "Оружейник", "Hunter": "Охотник", "Irwin": "Ирвин", "Isaac": "Айзек", "Kaleb": "Кейлеб", "Kasey": "Кейси", "Kirby": "Кирби", "Koy": "Кой", "Llamar": "Ламар", "Lynn": "Линн", "Majul": "Маджул", "Medic": "Медик", "Melvin": "Мелвин", "Messiah": "Мессия", "Muldraugh": "Малдро", "Officer": "Офицер", "Omega": "Омега", "Operator": "Оператор", "Oscar": "Оскар", "Pate": "Пейт", "Peyton": "Пейтон", "Pheonix": "Феникс", "Philip": "Филип", "Proto": "Прото", "Quincy": "Куинси", "Reese": "Риз", "Robin": "Малиновка", "Stitch": "Стич", "Tacti": "Тактик", "Tinkerer": "Механик", "Trill": "Трилл", "Trim": "Стройняшка", "Umbra": "Умбра", "Unit": "Юнит", "Watcher": "Созерцатель", "Weston": "Уэстон", "Wick": "Уик", "Zhang": "Чжан"}}, "ICKE": {"names": ["Adder", "Asshat", "Bam", "Bastard", "Benry", "Blythe", "Bo", "Bolter", "Boston", "Brandon", "Brawler", "Brent", "Brett", "Brock", "Brute", "Bryce", "Bryson", "Buck", "Bully", "Bunny", "Buster", "Calibre", "Carl", "Carrot", "Chad", "Chet", "Chuck", "Cody", "Crash", "David", "Dell", "Denise", "Devan", "Dominic", "Duke", "Dylan", "Easel", "Edlan", "Enzo", "Fighter", "Fletcher", "Floyd", "Fritz", "Gerson", "Glock", "Grove", "Gumpy", "Hain", "Hitch", "Hopper", "Hunter", "Isiah", "Jack", "Jacob", "Jagger", "Jeremy", "Jericho", "Jeter", "Jethro", "Joe", "Johnny", "Jumper", "Justin", "Kaige", "Kaleb", "Kent", "Kicker", "Kyle", "Landon", "Leon", "Link", "Lito", "Manuel", "Max", "Mitch", "Nailer", "Necksnapper", "Nolan", "Odell", "Palmer", "Peyton", "Potato", "Punk", "Rafeal", "Raig", "Randal", "Randy", "Ringo", "Ripply", "Roamer", "Ronteal", "Rude", "Ryder", "Ryne", "Sanchez", "Scout", "Sebastian", "Sigmund", "Skipper", "Smith", "Sniper", "Soldier", "Spencer", "Taegen", "Thug", "Thumper", "Toler", "Tophat", "Toreno", "Trickster", "Trodder", "Tucker", "Turner", "Wally", "Wayne", "Wowza", "Zare", "Zayne", "Zeke"], "canon": {"Adder": "Гадюка", "Bam": "Бам", "Bastard": "Ублюдок", "Benry": "Бенри", "Blythe": "Блайт", "Bo": "Бо", "Boston": "Бостон", "Brandon": "Брэндон", "Brent": "Брент", "Brett": "Бретт", "Brock": "Брок", "Brute": "Громила", "Bryce": "Брайс", "Buck": "Бак", "Calibre": "Калибр", "Carl": "Карл", "Carrot": "Морковка", "Chad": "Чад", "Chuck": "Чак", "Crash": "Крэш", "David": "Дэвид", "Denise": "Дениз", "Devan": "Деван", "Dominic": "Доминик", "Dylan": "Дилан", "Easel": "Изель", "Fritz": "Фриц", "Gerson": "Герсон", "Glock": "Глок", "Grove": "Роща", "Gumpy": "Гампи", "Hain": "Хейн", "Hitch": "Хитч", "Hopper": "Кузнечик", "Hunter": "Охотник", "Isiah": "Исайя", "Jack": "Джек", "Jacob": "Джейкоб", "Jagger": "Джаггер", "Jeremy": "Джереми", "Jethro": "Джетро", "Joe": "Джо", "Johnny": "Джонни", "Jumper": "Прыгун", "Kaleb": "Кейлеб", "Kent": "Кент", "Kyle": "Кайл", "Landon": "Лэндон", "Link": "Линк", "Manuel": "Мануэль", "Max": "Макс", "Mitch": "Митч", "Nailer": "Гвоздобой", "Odell": "Оделл", "Palmer": "Палмер", "Peyton": "Пейтон", "Raig": "Рейг", "Randal": "Рэндал", "Randy": "Рэнди", "Ringo": "Ринго", "Ripply": "Рябь", "Ronteal": "Ронтил", "Rude": "Руд", "Scout": "Разведчик", "Smith": "Смит", "Sniper": "Снайпер", "Soldier": "Солдат", "Spencer": "Спенсер", "Thumper": "Топотун", "Toler": "Толер", "Wally": "Уолли", "Wayne": "Уэйн", "Zare": "Зейр"}}, "SHELLY": {"names": ["Acid", "Aegis", "Alexandra", "Araceli", "Arian", "Armageddon", "Armor", "Astrid", "Athena", "Beast", "Bertha", "Bethany", "Bexley", "Blight", "Bridget", "Buddy", "Bulwark", "Calamity", "Cassidy", "Choi", "Corbus", "Crest", "Cyrene", "Daraus", "Deca", "Decius", "Denali", "Dianne", "Eavi", "Echo", "Elexa", "Enkil", "Ewa", "Fernanda", "Fort", "Frankie", "Gina", "Glowy", "Guardian", "Hannath", "Heather", "Hermione", "Hornet", "Hydra", "Hyedri", "Imara", "Imogen", "Isadora", "Ishva", "Ivy", "Ixii", "Jade", "Josephine", "Kara", "Karatus", "Kassie", "Katara", "Kate", "Kel", "Kele", "Kelsii", "Kendl", "Keon", "Kifflom", "Kirsten", "Leah", "Leonne", "Lilain", "Lime", "Lindsey", "Lue", "Mantis", "Marina", "Maritus", "Matilda", "Mijo", "Mildred", "Misty", "Molly", "Musa", "Novia", "Octavia", "Olexa", "Orion", "Orkin", "Paige", "Phobie", "Pinchy", "Queen", "Quilly", "Quincy", "Quintana", "Radi", "Radian", "Raig", "Razor", "Rocket", "Rumplet", "Sanford", "Saran", "Scorch", "Scorpian", "Severus", "Shale", "Sigmus", "Solara", "Solarius", "Song", "Sphinx", "Stomper", "Sulfur", "Summer", "Sylvia", "Taliama", "Terra", "Thumper", "Thyra", "Tomo", "Tower", "Trinity", "Trish", "Ulceria", "Ulsar", "Unit", "Valerie", "Venom", "Vernon", "Villie", "Wilma", "Wylda", "Xandra", "Xargo", "Xenia", "Zaila", "Zhora", "Zolaie", "Zondker", "Zorom", "Zully", "Zulmea"], "canon": {"Buddy": "Бадди", "Choi": "Чой", "Eavi": "Иви", "Ewa": "Эва", "Fort": "Форт", "Ivy": "Плющ", "Kate": "Кейт", "Kel": "Кел", "Kele": "Келе", "Lue": "Лю", "Mantis": "Мантис", "Misty": "Мисти", "Musa": "Муса", "Orion": "Орион", "Paige": "Пейдж", "Quilly": "Квилли", "Quincy": "Куинси", "Raig": "Рейг", "Razor": "Бритва", "Rocket": "Ракета", "Sanford": "Сэнфорд", "Scorch": "Скорч", "Song": "Сонг", "Sulfur": "Сера", "Sylvia": "Сильвия", "Thumper": "Топотун", "Unit": "Юнит", "Vernon": "Вернон", "Zondker": "Зондкер"}}, "DUNE": {"names": ["A", "Acid", "Agash", "Animal", "Axe", "Baal", "Bam", "Barrel", "Bastard", "Bibby", "Blade", "Bleeder", "Blight", "Blood", "Boom", "Brain", "Burrow", "Cane", "Cannibal", "Carlos", "Carne", "Chum", "Claw", "Cleaver", "Clog", "Cog", "Craw", "Crawler", "Creature", "Cyanide", "Dagger", "Demon", "Destroyer", "Dog", "Drone", "Dune", "E", "Eater", "Eyeball", "Failure", "Fallen", "Food", "Gaar", "Gho", "Ghug", "Gleeb", "Glock", "Gnat", "God", "Golon", "Gon", "Goopy", "Gorgon", "Gorlock", "Goss", "Grungler", "Gug", "Gul", "Gulgo", "Gun", "Gurgler", "Gutter", "Havoc", "Heart", "Hook", "Hornet", "I", "Ibilis", "Igor", "Ivan", "Jelly", "Kel", "Kidney", "Kifflom", "Knife", "Koy", "Licker", "Liver", "Loobie", "Lurker", "Madhu", "Malkeeth", "Man-Eater", "Maniac", "Mantis", "Mijo", "Mindless", "Mog", "Molug", "Nerve", "Nimue", "O", "Pal", "Pancreas", "Payne", "Peeper", "Philip", "Piercer", "Plague", "Prototype", "Quangus", "Queef", "Quilly", "Rabid", "Raider", "Rambo", "Render", "Ripper", "Rivulet", "Root", "Rouge", "Rumpel", "Sandy", "Sawblade", "Scorch", "Scrungle", "Scuggly", "Shrub", "Skull", "Spiker", "Spine", "Spleen", "Squimbly", "Stoic", "Stomach", "Striker", "Sulfur", "Sword", "Theno", "Thorax", "Toothy", "Traitor", "Twitchy", "Typhon", "U", "Uhl", "Ulsar", "Vandal", "Vein", "Wicked", "Wolzal", "X", "Y", "Z", "Zagan", "Zolag"], "canon": {"Bam": "Бам", "Barrel": "Бочка", "Bastard": "Ублюдок", "Blade": "Клинок", "Blood": "Кровь", "Boom": "Бабах", "Carlos": "Карлос", "Chum": "Кореш", "Claw": "Коготь", "Craw": "Крав", "Crawler": "Ползун", "Cyanide": "Цианид", "Food": "Жрачка", "Glock": "Глок", "Jelly": "Медузка", "Kel": "Кел", "Knife": "Нож", "Koy": "Кой", "Mantis": "Мантис", "Pal": "Дружок", "Peeper": "Гляделкинс", "Philip": "Филип", "Piercer": "Бронебой", "Quilly": "Квилли", "Rambo": "Рэмбо", "Render": "Раздиратель", "Ripper": "Потрошитель", "Rivulet": "Ручей", "Root": "Корень", "Rumpel": "Румпель", "Sawblade": "Циркулярка", "Scorch": "Скорч", "Scrungle": "Скрангл", "Scuggly": "Скаггли", "Shrub": "Кустик", "Sulfur": "Сера", "Sword": "Меч", "Theno": "Тено", "Toothy": "Зубастик", "X": "Икс"}}, "CRYSTAL": {"names": ["Adder", "Aija", "Allen", "Amber", "Amelia", "Amethyst", "Ananke", "Andrew", "Annie", "Anya", "Athena", "Aurora", "Azazel", "Azula", "Beatrix", "Beretta", "Bertha", "Beverly", "Blythe", "Bolt", "Brent", "Brook", "Buddy", "Cadmi", "Cameron", "Carl", "Carlos", "Catch", "Celeste", "Chum", "Church", "Clara", "Clog", "Cocoa", "Cole", "Colette", "Crest", "Crettin", "Crystal", "Danaa", "Daphne", "Daria", "Darthy", "David", "Deker", "Dell", "Delli", "Denise", "Dero", "Desmond", "Devan", "Dexter", "Diamond", "Dino", "Draco", "Dragon", "Dragonite", "Dreamfyre", "Drogon", "Dude", "Eavi", "Edgar", "Elara", "Elmer", "Eric", "Ersa", "Felix", "Fly-Eater", "Fort", "Freckles", "Frida", "Gabby", "Gali", "Garnet", "Geck", "Gizzy", "Gloria", "Goss", "Graphite", "Gravel", "Grey", "Growler", "Gumpy", "Gunsmith", "Harriet", "Heather", "Helike", "Hook", "Hornet", "Isiah", "Isy", "Ivan", "Iver", "Ivie", "Ixin", "JC", "Jack", "Jade", "James", "Jameson", "Jane", "Jean", "Jerry", "Jorge", "Joseph", "Kaleb", "Kalesh", "Kendl", "Kent", "Keon", "Keystone", "Kira", "Kirin", "Koch", "Kolov", "Lacky", "Landon", "Lapis", "Laz", "Lazlow", "Leda", "Leia", "Leon", "Lester", "Licker", "Link", "Lizard", "Lizus", "Lizzy", "Luken", "Lynn", "Lyubov", "Mantis", "Matt", "May", "Metii", "Micah", "Milikan", "Millar", "Misha", "Misty", "Mitch", "Mitchel", "Mitri", "Morgan", "Nathan", "Nathon", "Nera", "Nerret", "Niko", "Odell", "Onyx", "Opal", "Pandia", "Pearl", "Peyton", "Pheobe", "Philip", "Phobos", "Pibb", "Polina", "Punk", "Puzzle", "Quartz", "Quincy", "Radi", "Randal", "Raven", "Raymon", "Rhea", "Ripply", "Ronteal", "Roph", "Rubin", "Ruby", "Rumpel", "Ruth", "Ryker", "Samus", "Saphira", "Sasha", "Scaley", "Scar", "Scratch", "Sergey", "Shelby", "Shenron", "Shrub", "Simeon", "Simon", "Skylar", "Slider", "Slunki", "Snatcher", "Soldier", "Sphinx", "Steel", "Steven", "Stormfly", "Taegen", "Tanya", "Teri", "Terrin", "Teymac", "Thebe", "Theo", "Thomas", "Thomi", "Thorn", "Tina", "Tobia", "Togu", "Toler", "Tony", "Topaz", "Topher", "Trapper", "Trish", "Trudy", "Tural", "Ulysses", "Val", "Valeria", "Valonov", "Vector", "Venus", "Vesper", "Vicktor", "Viktoria", "Vilard", "Vince", "Vise", "Vutan", "Wade", "Waidie", "Wally", "Walter", "Wesson", "Wick", "Will", "Wyvern", "Xenia", "Yoinky", "Yuki", "Zander", "Zoie", "Zora"], "canon": {"Adder": "Гадюка", "Aija": "Айя", "Allen": "Аллен", "Andrew": "Эндрю", "Annie": "Энни", "Azula": "Азула", "Beverly": "Беверли", "Blythe": "Блайт", "Bolt": "Болт", "Brent": "Брент", "Brook": "Брук", "Buddy": "Бадди", "Carl": "Карл", "Carlos": "Карлос", "Celeste": "Селеста", "Chum": "Кореш", "Church": "Церковь", "Cocoa": "Какао", "Cole": "Коул", "Crystal": "Кристал", "David": "Дэвид", "Deker": "Декер", "Denise": "Дениз", "Desmond": "Десмонд", "Devan": "Деван", "Dragon": "Дракон", "Dude": "Чувак", "Eavi": "Иви", "Edgar": "Эдгар", "Elmer": "Элмер", "Eric": "Эрик", "Felix": "Феликс", "Fort": "Форт", "Gabby": "Габби", "Gravel": "Гравий", "Grey": "Серый", "Growler": "Рычун", "Gumpy": "Гампи", "Gunsmith": "Оружейник", "Isiah": "Исайя", "Iver": "Ивер", "JC": "Джей-Си", "Jack": "Джек", "James": "Джеймс", "Jameson": "Джеймсон", "Jerry": "Джерри", "Jorge": "Хорхе", "Joseph": "Джозеф", "Kaleb": "Кейлеб", "Kent": "Кент", "Koch": "Кох", "Lacky": "Шестёрка", "Landon": "Лэндон", "Lazlow": "Лазлоу", "Lester": "Лестер", "Link": "Линк", "Luken": "Лукен", "Lynn": "Линн", "Mantis": "Мантис", "Matt": "Мэтт", "Misty": "Мисти", "Mitch": "Митч", "Mitchel": "Митчел", "Mitri": "Митри", "Nathan": "Нейтан", "Odell": "Оделл", "Onyx": "Оникс", "Peyton": "Пейтон", "Philip": "Филип", "Pibb": "Пибб", "Quincy": "Куинси", "Randal": "Рэндал", "Raymon": "Реймон", "Ripply": "Рябь", "Ronteal": "Ронтил", "Roph": "Роф", "Ruby": "Руби", "Rumpel": "Румпель", "Ruth": "Рут", "Scratch": "Коготок", "Sergey": "Сергей", "Shrub": "Кустик", "Simeon": "Симеон", "Simon": "Саймон", "Skylar": "Скайлар", "Snatcher": "Похититель", "Soldier": "Солдат", "Steel": "Сталь", "Steven": "Стивен", "Teri": "Тери", "Theo": "Тео", "Thomas": "Томас", "Tobia": "Тобиа", "Toler": "Толер", "Topher": "Тофер", "Trapper": "Минёр", "Tural": "Турал", "Venus": "Венера", "Vesper": "Веспер", "Vilard": "Вилард", "Vise": "Тиски", "Vutan": "Вутан", "Wade": "Уэйд", "Wally": "Уолли", "Walter": "Уолтер", "Wesson": "Вессон", "Wick": "Уик", "Will": "Уилл", "Yoinky": "Йоинки", "Yuki": "Юки", "Zander": "Зандер"}, "pool_main": ["Adder", "Aija", "Allen", "Amber", "Amelia", "Amethyst", "Ananke", "Annie", "Anya", "Athena", "Aurora", "Azula", "Beatrix", "Beretta", "Bertha", "Beverly", "Bolt", "Brook", "Cadmi", "Celeste", "Chum", "Clara", "Cocoa", "Colette", "Crest", "Crettin", "Crystal", "Danaa", "Daphne", "Daria", "Darthy", "Deker", "Delli", "Diamond", "Dragonite", "Dreamfyre", "Drogon", "Dude", "Eavi", "Elara", "Ersa", "Freckles", "Frida", "Gabby", "Gali", "Garnet", "Gizzy", "Gloria", "Graphite", "Growler", "Harriet", "Heather", "Helike", "Hornet", "Isy", "Ivie", "Jade", "Jane", "Jean", "Kendl", "Keon", "Keystone", "Kira", "Kirin", "Lacky", "Lapis", "Laz", "Leda", "Leia", "Licker", "Lizard", "Lizzy", "Lyubov", "Mantis", "May", "Metii", "Misty", "Morgan", "Nera", "Onyx", "Opal", "Pandia", "Pearl", "Pheobe", "Pibb", "Polina", "Punk", "Radi", "Raven", "Rhea", "Roph", "Ruby", "Ruth", "Ryker", "Saphira", "Sasha", "Scaley", "Scar", "Scratch", "Shelby", "Shenron", "Skylar", "Slunki", "Snatcher", "Sphinx", "Stormfly", "Tanya", "Teymac", "Thebe", "Thomi", "Thorn", "Tina", "Tobia", "Topaz", "Topher", "Trapper", "Trish", "Trudy", "Tural", "Val", "Venus", "Vesper", "Viktoria", "Vise", "Waidie", "Wesson", "Wyvern", "Xenia", "Yoinky", "Zoie", "Zora"], "pool_trans": ["Adder", "Allen", "Andrew", "Azazel", "Beverly", "Blythe", "Bolt", "Brent", "Buddy", "Cameron", "Carl", "Carlos", "Catch", "Chum", "Church", "Clog", "Cole", "Crettin", "David", "Dell", "Denise", "Dero", "Desmond", "Devan", "Dexter", "Diamond", "Dino", "Draco", "Dragon", "Dragonite", "Dreamfyre", "Drogon", "Dude", "Edgar", "Elmer", "Eric", "Felix", "Fly-Eater", "Fort", "Geck", "Goss", "Gravel", "Grey", "Growler", "Gumpy", "Gunsmith", "Hook", "Hornet", "Isiah", "Ivan", "Iver", "Ixin", "JC", "Jack", "James", "Jameson", "Jerry", "Jorge", "Joseph", "Kaleb", "Kalesh", "Kent", "Koch", "Kolov", "Lacky", "Landon", "Lazlow", "Leon", "Lester", "Link", "Lizard", "Lizus", "Luken", "Lynn", "Mantis", "Matt", "Micah", "Milikan", "Millar", "Misha", "Mitch", "Mitchel", "Mitri", "Nathan", "Nathon", "Nerret", "Niko", "Odell", "Onyx", "Opal", "Peyton", "Philip", "Phobos", "Punk", "Puzzle", "Quartz", "Quincy", "Randal", "Raymon", "Ripply", "Ronteal", "Roph", "Rubin", "Rumpel", "Samus", "Scaley", "Scar", "Scratch", "Sergey", "Shrub", "Simeon", "Simon", "Skylar", "Slider", "Slunki", "Snatcher", "Soldier", "Steel", "Steven", "Taegen", "Teri", "Terrin", "Teymac", "Theo", "Thomas", "Togu", "Toler", "Tony", "Topaz", "Trapper", "Trish", "Ulysses", "Val", "Valeria", "Valonov", "Vector", "Vesper", "Vicktor", "Vilard", "Vince", "Vise", "Vutan", "Wade", "Wally", "Walter", "Wesson", "Wick", "Will", "Yoinky", "Yuki", "Zander"]}, "VELVET": {"names": ["6 Eyes", "6 Legs", "Abaddon", "Abigail", "Abraxas", "Acheron", "Achlys", "Ajax", "Akuma", "Amber", "Anoth", "Anwir", "Azazel", "Baker", "Balor", "Bane", "Banshee", "Bastard", "Beauty", "Bertha", "Bienor", "Black", "Blight", "Blythe", "Bracken", "Brackie", "Carna", "Carnate", "Carne", "Catherine", "Ceasar", "Cerebus", "Chef", "Chopper", "Chuck", "Church", "Colette", "Corbus", "Crawler", "Creature", "Crest", "Crimson", "Crone", "Daemon", "Daisy", "Dante", "Darthy", "Dementia", "Derra", "Desmond", "Devan", "Deyth", "Dianne", "Dolion", "Donna", "Dorien", "Draven", "Duke", "Edgar", "Elijah", "Elliot", "Elma", "Elmer", "Elvira", "Eris", "Europa", "Ewa", "Fabi", "Fabian", "Father", "Forelli", "Fort", "Gail", "Ghost", "God", "Goss", "Gregori", "Growler", "Hades", "Hazel", "Heather", "Hecate", "Helge", "Hissy", "Hitch", "Hunter", "Idris", "Isabelle", "Isiaus", "Iver", "Ixion", "Jethro", "Judy", "Kalon", "Kathy", "Keegan", "Kele", "Kentty", "Kuru", "Larkus", "Leonne", "Lilith", "Lily", "Lola", "Loomis", "Lucia", "Lucian", "Lue", "Luken", "Lurker", "Lysine", "Madhu", "Majorie", "Majul", "Man-Eater", "Mania", "Mantis", "Margaret", "Margot", "Martha", "Marthus", "Mathius", "Merle", "Millar", "Milly", "Milton", "Misty", "Monarch", "Moon", "Morgoth", "Moros", "Morose", "Mortis", "Mother", "Muffet", "Mura", "Nancy", "Natu", "Nemisis", "Neonty", "Nephilim", "Nirvana", "Nixxin", "Nox", "Nurse", "Nyx", "Observer", "Octavia", "Odette", "Ophelia", "Orcian", "Ormr", "Palathin", "Patriarch", "Penelope", "Phantom", "Phobos", "Plague", "Prince", "Prowler", "Psyche", "Queen", "Quelaag", "Quelan", "Quelana", "Queluin", "Quilly", "Quintana", "Raven", "Reaper", "Render", "Rigor", "Ronteal", "Rue", "Samantha", "Scarlett", "Sephtis", "Seraphina", "Serpent", "Seth", "Shadow", "Sherrea", "Sigmund", "Silence", "Sindacco", "Sister", "Skull", "Snake", "Snatcher", "Song", "Spider", "Squimbly", "Stalker", "Sweetheart", "Sweetie", "Sword", "Sylvia", "Taegen", "Taliama", "Terra", "Terror", "Thalia", "Themis", "Thomas", "Thomi", "Thora", "Thorn", "Titan", "Toler", "Torris", "Tranch", "Trapper", "Tulip", "Tural", "Ulsar", "Umbra", "Velvet", "Venus", "Veronica", "Vestina", "Vilard", "Villie", "Vito", "Voodoo", "Vutan", "Weaver", "Webber", "Whisper", "Wine", "Wrath", "Zagan", "Zedd", "Zondker"], "canon": {"Anoth": "Анот", "Bastard": "Ублюдок", "Black": "Чёрный", "Blythe": "Блайт", "Chef": "Шеф", "Chuck": "Чак", "Church": "Церковь", "Crawler": "Ползун", "Desmond": "Десмонд", "Devan": "Деван", "Edgar": "Эдгар", "Elliot": "Эллиот", "Elmer": "Элмер", "Ewa": "Эва", "Fabi": "Фаби", "Fort": "Форт", "Ghost": "Гоуст", "Gregori": "Григорий", "Growler": "Рычун", "Hazel": "Хейзел", "Hitch": "Хитч", "Hunter": "Охотник", "Idris": "Идрис", "Isabelle": "Изабель", "Iver": "Ивер", "Jethro": "Джетро", "Judy": "Джуди", "Keegan": "Киган", "Kele": "Келе", "Lily": "Лили", "Lola": "Лола", "Lue": "Лю", "Luken": "Лукен", "Majul": "Маджул", "Mantis": "Мантис", "Milly": "Милли", "Milton": "Милтон", "Misty": "Мисти", "Moon": "Луна", "Morose": "Угрюмый", "Mortis": "Мортис", "Natu": "Нату", "Nirvana": "Нирвана", "Phantom": "Фантом", "Quilly": "Квилли", "Render": "Раздиратель", "Ronteal": "Ронтил", "Seth": "Сиф", "Shadow": "Тень", "Silence": "Тишина", "Snake": "Снейк", "Snatcher": "Похититель", "Song": "Сонг", "Sweetheart": "Милая", "Sword": "Меч", "Sylvia": "Сильвия", "Thomas": "Томас", "Toler": "Толер", "Trapper": "Минёр", "Tural": "Турал", "Umbra": "Умбра", "Venus": "Венера", "Vilard": "Вилард", "Voodoo": "Вуду", "Vutan": "Вутан", "Zondker": "Зондкер"}, "pool_main": ["6 Eyes", "6 Legs", "Abigail", "Achlys", "Amber", "Anoth", "Baker", "Banshee", "Beauty", "Bertha", "Blight", "Brackie", "Carna", "Catherine", "Chef", "Chopper", "Colette", "Crawler", "Creature", "Crest", "Crimson", "Daisy", "Darthy", "Dementia", "Derra", "Dianne", "Donna", "Elma", "Elvira", "Europa", "Ewa", "Fabi", "Forelli", "Gail", "Growler", "Hazel", "Heather", "Hissy", "Hunter", "Isabelle", "Iver", "Judy", "Kathy", "Kele", "Kentty", "Kuru", "Lilith", "Lily", "Lola", "Lucia", "Lue", "Lurker", "Lysine", "Majul", "Mania", "Margaret", "Margot", "Martha", "Marthus", "Merle", "Milly", "Misty", "Monarch", "Moon", "Morose", "Mother", "Muffet", "Mura", "Nancy", "Nox", "Nyx", "Observer", "Octavia", "Odette", "Ophelia", "Penelope", "Prowler", "Queen", "Quelaag", "Quelana", "Quilly", "Quintana", "Raven", "Rue", "Samantha", "Scarlett", "Seraphina", "Shadow", "Sherrea", "Silence", "Sister", "Snake", "Snatcher", "Song", "Spider", "Squimbly", "Stalker", "Sweetheart", "Sweetie", "Sylvia", "Terra", "Thalia", "Thomi", "Thora", "Tranch", "Trapper", "Tulip", "Tural", "Umbra", "Velvet", "Venus", "Veronica", "Vestina", "Villie", "Voodoo", "Weaver", "Webber", "Whisper", "Wine", "Wrath", "Zondker"], "pool_trans": ["6 Eyes", "6 Legs", "Abaddon", "Abraxas", "Acheron", "Ajax", "Akuma", "Anoth", "Anwir", "Azazel", "Balor", "Bane", "Bastard", "Bienor", "Black", "Blythe", "Bracken", "Carnate", "Carne", "Ceasar", "Cerebus", "Chef", "Chuck", "Church", "Corbus", "Crawler", "Creature", "Crone", "Daemon", "Dante", "Desmond", "Devan", "Deyth", "Dolion", "Dorien", "Draven", "Duke", "Edgar", "Elijah", "Elliot", "Elmer", "Eris", "Fabian", "Father", "Forelli", "Fort", "Ghost", "God", "Goss", "Gregori", "Growler", "Hades", "Hecate", "Helge", "Hitch", "Hunter", "Idris", "Isiaus", "Ixion", "Jethro", "Kalon", "Keegan", "Kuru", "Larkus", "Leonne", "Loomis", "Lucian", "Luken", "Lurker", "Madhu", "Majorie", "Man-Eater", "Mantis", "Mathius", "Millar", "Milton", "Morgoth", "Moros", "Morose", "Mortis", "Natu", "Nemisis", "Neonty", "Nephilim", "Nirvana", "Nixxin", "Nox", "Nurse", "Observer", "Orcian", "Ormr", "Palathin", "Patriarch", "Phantom", "Phobos", "Plague", "Prince", "Prowler", "Psyche", "Quelan", "Queluin", "Reaper", "Render", "Rigor", "Ronteal", "Sephtis", "Serpent", "Seth", "Sigmund", "Sindacco", "Skull", "Snake", "Snatcher", "Stalker", "Sword", "Taegen", "Taliama", "Terror", "Themis", "Thomas", "Thorn", "Titan", "Toler", "Torris", "Tranch", "Trapper", "Ulsar", "Vilard", "Vito", "Vutan", "Weaver", "Webber", "Zagan", "Zedd"]}}